{
	"configurations" : 
	[
		{
			"directories" : 
			[
				{
					"build" : ".",
					"childIndexes" : 
					[
						1
					],
					"hasInstallRule" : true,
					"minimumCMakeVersion" : 
					{
						"string" : "3.15"
					},
					"projectIndex" : 0,
					"source" : ".",
					"targetIndexes" : 
					[
						0
					]
				},
				{
					"build" : "externals",
					"childIndexes" : 
					[
						2
					],
					"hasInstallRule" : true,
					"minimumCMakeVersion" : 
					{
						"string" : "3.15"
					},
					"parentIndex" : 0,
					"projectIndex" : 0,
					"source" : "externals"
				},
				{
					"build" : "externals/tinyobjloader",
					"hasInstallRule" : true,
					"minimumCMakeVersion" : 
					{
						"string" : "3.2"
					},
					"parentIndex" : 1,
					"projectIndex" : 1,
					"source" : "externals/tinyobjloader",
					"targetIndexes" : 
					[
						1,
						2
					]
				}
			],
			"name" : "Debug",
			"projects" : 
			[
				{
					"childIndexes" : 
					[
						1
					],
					"directoryIndexes" : 
					[
						0,
						1
					],
					"name" : "Moer-lite",
					"targetIndexes" : 
					[
						0
					]
				},
				{
					"directoryIndexes" : 
					[
						2
					],
					"name" : "tinyobjloader",
					"parentIndex" : 0,
					"targetIndexes" : 
					[
						1,
						2
					]
				}
			],
			"targets" : 
			[
				{
					"directoryIndex" : 0,
					"id" : "Moer::@6890427a1f51a3e7e1df",
					"jsonFile" : "target-Moer-Debug-0e29d34907665b1e8e31.json",
					"name" : "Moer",
					"projectIndex" : 0
				},
				{
					"directoryIndex" : 2,
					"id" : "tinyobjloader::@dfbdfcb24b966a616c46",
					"jsonFile" : "target-tinyobjloader-Debug-c0a8710ceecfb211e27e.json",
					"name" : "tinyobjloader",
					"projectIndex" : 1
				},
				{
					"directoryIndex" : 2,
					"id" : "uninstall::@dfbdfcb24b966a616c46",
					"jsonFile" : "target-uninstall-Debug-2a0e1992bf889174c31e.json",
					"name" : "uninstall",
					"projectIndex" : 1
				}
			]
		}
	],
	"kind" : "codemodel",
	"paths" : 
	{
		"build" : "E:/code/2023spr/Moer-lite/out/build/x64-Debug",
		"source" : "E:/code/2023spr/Moer-lite"
	},
	"version" : 
	{
		"major" : 2,
		"minor" : 2
	}
}
